aiogtrans/__init__.py
aiogtrans/cache.py
aiogtrans/client.py
aiogtrans/constants.py
aiogtrans/models.py
aiogtrans/urls.py
aiogtrans_proxy-1.1.25.dist-info/LICENSE
aiogtrans_proxy-1.1.25.dist-info/METADATA
aiogtrans_proxy-1.1.25.dist-info/WHEEL
aiogtrans_proxy-1.1.25.dist-info/top_level.txt
aiogtrans_proxy-1.1.25.dist-info/RECORD
