Metadata-Version: 2.2
Name: aiogtrans-proxy
Version: 1.1.25
Summary: An async and updated version of the googletrans package.
Home-page: https://github.com/ivan-khomich/aiogtrans
Author: ivanxo
Author-email: ivan.khomich@gmail.com
License: MIT
Keywords: google translate translator async
Classifier: Development Status :: 5 - Production/Stable
Classifier: Intended Audience :: Education
Classifier: Intended Audience :: End Users/Desktop
Classifier: License :: Freeware
Classifier: Operating System :: POSIX
Classifier: Operating System :: Microsoft :: Windows
Classifier: Operating System :: MacOS :: MacOS X
Classifier: Topic :: Education
Classifier: Programming Language :: Python
Classifier: Programming Language :: Python :: 3.9
Requires-Python: >=3.9
License-File: LICENSE
Requires-Dist: httpx<=0.27.0
Requires-Dist: setuptools==58.1.0
Dynamic: author
Dynamic: author-email
Dynamic: classifier
Dynamic: description
Dynamic: description-content-type
Dynamic: home-page
Dynamic: keywords
Dynamic: license
Dynamic: requires-dist
Dynamic: requires-python
Dynamic: summary
